textual_tty/__init__.py
textual_tty/__main__.py
textual_tty/demo.py
textual_tty/log.py
textual_tty/rich_cache.py
textual_tty/widgets/__init__.py
textual_tty/widgets/debug_log.py
textual_tty/widgets/terminal_app.py
textual_tty/widgets/terminal_scroll_view.py
textual_tty/widgets/textual_terminal.py
textual_tty-0.2.4.dist-info/entry_points.txt
textual_tty-0.2.4.dist-info/licenses/LICENSE.md
textual_tty-0.2.4.dist-info/WHEEL
textual_tty-0.2.4.dist-info/METADATA
textual_tty-0.2.4.dist-info/RECORD
