Metadata-Version: 2.4
Name: textual_tty
Version: 0.2.4
Summary: A tty for Textual UIs
Author-email: Gareth Davidson <gaz@bitplane.net>
Requires-Python: >=3.10
Classifier: Development Status :: 2 - Pre-Alpha
Classifier: Programming Language :: Python :: 3
Classifier: Programming Language :: Python :: 3.10
Classifier: Programming Language :: Python :: 3.11
Classifier: License :: Public Domain
Classifier: Environment :: Console
Classifier: Intended Audience :: Developers
License-File: LICENSE.md
Requires-Dist: textual
Requires-Dist: bittty==0.0.5
Requires-Dist: pywinpty ; sys_platform == 'win32'
Requires-Dist: textual-window~=0.8
Requires-Dist: pre-commit ; extra == "dev"
Requires-Dist: pytest ; extra == "dev"
Requires-Dist: pytest-asyncio ; extra == "dev"
Requires-Dist: coverage ; extra == "dev"
Requires-Dist: pytest-cov ; extra == "dev"
Requires-Dist: pydoc-markdown ; extra == "dev"
Requires-Dist: build ; extra == "dev"
Requires-Dist: twine ; extra == "dev"
Requires-Dist: ruff ; extra == "dev"
Requires-Dist: mkdocs ; extra == "dev"
Requires-Dist: mkdocs-material ; extra == "dev"
Requires-Dist: textual-window ; extra == "dev"
Project-URL: Bug Tracker, https://github.com/bitplane/textual-tty/issues
Project-URL: Homepage, https://bitplane.net/dev/python/textual-tty
Project-URL: Source Code, https://github.com/bitplane/textual-tty
Provides-Extra: dev
